<?xml version="1.0" encoding="UTF-8" standalone="no"?><Station><Status state="OK"/><Number>3321</Number><Name>МЕТРОСТАНЦИЯ МЕДИЦИНСКИ УНИВЕРСИТЕТ</Name><Direction>м.Хаджи Димитър - м.Красно Село</Direction><Coordinates><Latitude>42.686537</Latitude><Longitude>23.30932</Longitude></Coordinates><Schedule day="Weekday"><Time hour="4"/><Time hour="5">5:10,5:19,5:28,5:37,5:46,5:55</Time><Time hour="6">6:04,6:13,6:22,6:31,6:40,6:46,6:53,6:59</Time><Time hour="7">7:06,7:12,7:19,7:25,7:32,7:38,7:42,7:47,7:52,7:56</Time><Time hour="8">8:01,8:06,8:11,8:15,8:20,8:24,8:29,8:33,8:38,8:42,8:47,8:51,8:56</Time><Time hour="9">9:00,9:05,9:09,9:14,9:18,9:23,9:27,9:32,9:36,9:41,9:46,9:51,9:56</Time><Time hour="10">10:00,10:04,10:09,10:14,10:19,10:25,10:30,10:36,10:41,10:47,10:53,10:58</Time><Time hour="11">11:04,11:09,11:14,11:20,11:26,11:32,11:38,11:44,11:50,11:56</Time><Time hour="12">12:02,12:08,12:14,12:20,12:26,12:32,12:38,12:44,12:50,12:56</Time><Time hour="13">13:02,13:08,13:14,13:20,13:26,13:32,13:38,13:44,13:50,13:56</Time><Time hour="14">14:02,14:08,14:14,14:20,14:26,14:32,14:38,14:44,14:50,14:56</Time><Time hour="15">15:02,15:08,15:14,15:20,15:26,15:32,15:38,15:44,15:50,15:56</Time><Time hour="16">16:02,16:08,16:14,16:20,16:26,16:32,16:37,16:47,16:53,16:58</Time><Time hour="17">17:03,17:07,17:13,17:18,17:23,17:28,17:33,17:38,17:43,17:48,17:53,17:58</Time><Time hour="18">18:03,18:08,18:13,18:18,18:23,18:28,18:33,18:38,18:43,18:48,18:53,18:58</Time><Time hour="19">19:03,19:08,19:13,19:18,19:23,19:28,19:33,19:38,19:43,19:48,19:53,19:58</Time><Time hour="20">20:03,20:08,20:13,20:18,20:23,20:28,20:33,20:38,20:42,20:48,20:54</Time><Time hour="21">21:00,21:06,21:12,21:18,21:24,21:30,21:36,21:42,21:48,21:54</Time><Time hour="22">22:00,22:06,22:12,22:20,22:27,22:35,22:42,22:52</Time><Time hour="23">23:01,23:09,23:21,23:33,23:43,23:55</Time><Time hour="24"/></Schedule><Schedule day="Holiday"><Time hour="4"/><Time hour="5"/><Time hour="6"/><Time hour="7"/><Time hour="8"/><Time hour="9"/><Time hour="10"/><Time hour="11"/><Time hour="12"/><Time hour="13"/><Time hour="14"/><Time hour="15"/><Time hour="16"/><Time hour="17"/><Time hour="18"/><Time hour="19"/><Time hour="20"/><Time hour="21"/><Time hour="22"/><Time hour="23"/><Time hour="24"/></Schedule></Station>