<?xml version="1.0" encoding="UTF-8" standalone="no"?><Station><Status state="OK"/><Number>3017</Number><Name>МЕТРОСТАНЦИЯ СТ.ВАСИЛ ЛЕВСКИ</Name><Direction>м.Витоша - м.Обеля - м.Летище София</Direction><Coordinates><Latitude>42.686032</Latitude><Longitude>23.332043</Longitude></Coordinates><Schedule day="Weekday"><Time hour="4"/><Time hour="5">5:16,5:23,5:32|IC,5:39|IC,5:46|IC,5:53|IC,5:57</Time><Time hour="6">6:07|IC,6:13,6:20|IC,6:22|IC,6:28,6:35|IC,6:37|IC,6:42,6:49|IC,6:51|IC,6:56,6:58|IC</Time><Time hour="7">7:03|IC,7:05,7:10|IC,7:12,7:17|IC,7:19,7:24|IC,7:26|IC,7:31,7:33|IC,7:38,7:40|IC,7:45,7:47|IC,7:52,7:54|IC,7:59</Time><Time hour="8">8:01|IC,8:06,8:08|IC,8:13,8:15|IC,8:20,8:22|IC,8:27,8:29|IC,8:34,8:36|IC,8:41,8:43|IC,8:48,8:50|IC,8:55,8:57|IC</Time><Time hour="9">9:02,9:04|IC,9:09,9:11|IC,9:16,9:18|IC,9:23,9:25|IC,9:30,9:32|IC,9:37,9:39|IC,9:44,9:46|IC,9:50,9:53|IC,9:58</Time><Time hour="10">10:01|IC,10:08,10:11|IC,10:15,10:20,10:24,10:28|IC,10:33,10:38,10:42|IC,10:47,10:51|IC,10:56</Time><Time hour="11">11:00,11:04|IC,11:09,11:14|IC,11:18,11:23,11:27,11:31|IC,11:36,11:40|IC,11:45,11:50,11:56,11:58|IC</Time><Time hour="12">12:03,12:07|IC,12:12,12:16|IC,12:21,12:25|IC,12:30,12:34|IC,12:39,12:43|IC,12:48,12:52|IC,12:57</Time><Time hour="13">13:01|IC,13:06,13:10|IC,13:15,13:19|IC,13:24,13:28|IC,13:33,13:37|IC,13:42,13:46|IC,13:51,13:55|IC</Time><Time hour="14">14:00,14:04|IC,14:09,14:13|IC,14:18,14:22|IC,14:27,14:31|IC,14:36,14:40|IC,14:45,14:49|IC,14:54,14:58|IC</Time><Time hour="15">15:03,15:07|IC,15:12,15:16|IC,15:21,15:25|IC,15:30,15:34|IC,15:39,15:43|IC,15:48,15:52|IC,15:57</Time><Time hour="16">16:01|IC,16:06,16:10|IC,16:15,16:19|IC,16:24,16:28|IC,16:33,16:37|IC,16:42,16:47|IC,16:52,16:55|IC</Time><Time hour="17">17:00,17:03|IC,17:08,17:11|IC,17:16,17:19|IC,17:23,17:27|IC,17:32,17:35|IC,17:40,17:43|IC,17:48,17:51|IC,17:56,17:59|IC</Time><Time hour="18">18:04,18:07|IC,18:12,18:15|IC,18:20,18:23|IC,18:28,18:31|IC,18:36,18:39|IC,18:44,18:47|IC,18:52,18:55|IC</Time><Time hour="19">19:00,19:03|IC,19:08,19:11|IC,19:16,19:19|IC,19:24,19:27|IC,19:32,19:35|IC,19:40,19:43|IC,19:48,19:51|IC,19:56,19:59|IC</Time><Time hour="20">20:04,20:07|IC,20:12,20:15|IC,20:20,20:23|IC,20:29,20:34,20:40,20:44|IC,20:50,20:54|IC</Time><Time hour="21">21:00,21:04,21:10,21:14|IC,21:22,21:24|IC,21:30,21:34|IC,21:40,21:44,21:52,21:54|IC</Time><Time hour="22">22:03,22:06,22:14,22:18|IC,22:25,22:30|IC,22:37,22:42,22:50,22:55|IC</Time><Time hour="23">23:02,23:07|IC,23:16,23:22,23:31,23:35|IC,23:43,23:53</Time><Time hour="24"/></Schedule><Schedule day="Holiday"><Time hour="4"/><Time hour="5">5:16,5:26,5:35|IC,5:42|IC,5:50|IC,5:56|IC</Time><Time hour="6">6:01,6:10|IC,6:18,6:24|IC,6:32,6:38|IC,6:46,6:52|IC</Time><Time hour="7">7:00,7:05|IC,7:14,7:19|IC,7:28,7:33|IC,7:42,7:48|IC,7:56</Time><Time hour="8">8:02|IC,8:10,8:15|IC,8:24,8:29|IC,8:38,8:44|IC,8:51,8:55|IC</Time><Time hour="9">9:02,9:07|IC,9:14,9:20|IC,9:26,9:32|IC,9:40,9:44|IC,9:52,9:56|IC</Time><Time hour="10">10:03,10:09|IC,10:17,10:21|IC,10:29,10:33|IC,10:41,10:45|IC,10:53,10:58|IC</Time><Time hour="11">11:06,11:10|IC,11:17,11:22|IC,11:29,11:35|IC,11:41,11:47|IC,11:55,11:59|IC</Time><Time hour="12">12:07,12:12|IC,12:18,12:24|IC,12:30,12:36|IC,12:44,12:48|IC,12:56</Time><Time hour="13">13:01|IC,13:07,13:13|IC,13:21,13:25|IC,13:32,13:37|IC,13:44,13:50|IC,13:56</Time><Time hour="14">14:02|IC,14:10,14:14|IC,14:22,14:26|IC,14:33,14:39|IC,14:45,14:51|IC,14:59</Time><Time hour="15">15:03|IC,15:11,15:15|IC,15:23,15:28|IC,15:36,15:40|IC,15:47,15:53|IC,15:59</Time><Time hour="16">16:05|IC,16:11,16:16|IC,16:25,16:29|IC,16:37,16:42|IC,16:48,16:54|IC</Time><Time hour="17">17:00,17:06|IC,17:14,17:18|IC,17:26,17:30|IC,17:37,17:43|IC,17:51,17:55|IC</Time><Time hour="18">18:02,18:07|IC,18:14,18:20|IC,18:26,18:32|IC,18:40,18:44|IC,18:52,18:56|IC</Time><Time hour="19">19:03,19:09|IC,19:15,19:21|IC,19:29,19:33|IC,19:41,19:45|IC,19:52,19:58|IC</Time><Time hour="20">20:06,20:10|IC,20:17,20:23|IC,20:29,20:35|IC,20:42,20:48|IC,20:57</Time><Time hour="21">21:02|IC,21:11,21:16|IC,21:25,21:30|IC,21:39,21:45,21:54</Time><Time hour="22">22:01|IC,22:09,22:16|IC,22:24,22:32,22:41|IC,22:46,22:55|IC</Time><Time hour="23">23:01,23:10|IC,23:16,23:24|IC,23:31,23:40|IC</Time><Time hour="24"/></Schedule></Station>