<?xml version="1.0" encoding="UTF-8" standalone="no"?><Station><Status state="OK"/><Number>2976</Number><Name>МЕТРОСТАНЦИЯ ВИТОША</Name><Direction>м.Младост 1 - м.Обеля - м.Витоша</Direction><Coordinates><Latitude>42.6584210571113</Latitude><Longitude>23.3164127099729</Longitude></Coordinates><Schedule day="Weekday"><Time hour="4"/><Time hour="5">5:22,5:36|IC,5:47|IC,5:59|IC</Time><Time hour="6">6:09|IC,6:21,6:32,6:40,6:46,6:52,6:58</Time><Time hour="7">7:04,7:10,7:16,7:22,7:28,7:34,7:40,7:46,7:52,7:58</Time><Time hour="8">8:04,8:10,8:16,8:22,8:28,8:34,8:40,8:46,8:52,8:58</Time><Time hour="9">9:04,9:10,9:16,9:22,9:28,9:34,9:40,9:46,9:52,9:58</Time><Time hour="10">10:04,10:10,10:16,10:22,10:31,10:37,10:46,10:52,10:58</Time><Time hour="11">11:04,11:10,11:15,11:22,11:31,11:40,11:49,11:58</Time><Time hour="12">12:07,12:16,12:25,12:34,12:43,12:52</Time><Time hour="13">13:01,13:10,13:19,13:28,13:37,13:46,13:55</Time><Time hour="14">14:04,14:13,14:22,14:31,14:40,14:49,14:58</Time><Time hour="15">15:07,15:16,15:25,15:34,15:43,15:52</Time><Time hour="16">16:01,16:10,16:15,16:24,16:33,16:37,16:46,16:55</Time><Time hour="17">17:00,17:09,17:18,17:22,17:31,17:40,17:45,17:54</Time><Time hour="18">18:02,18:11,18:15,18:24,18:31,18:39,18:46,18:54</Time><Time hour="19">19:01,19:09,19:16,19:24,19:31,19:39,19:46,19:54</Time><Time hour="20">20:01,20:09,20:20,20:27,20:34,20:41,20:45,20:54</Time><Time hour="21">21:01,21:09,21:17,21:25,21:33,21:41,21:49,21:58</Time><Time hour="22">22:08,22:20,22:31,22:44,22:58</Time><Time hour="23">23:12,23:27,23:42,23:57</Time><Time hour="24">0:06</Time></Schedule><Schedule day="Holiday"><Time hour="4"/><Time hour="5">5:24,5:41|IC,5:55|IC</Time><Time hour="6">6:09|IC,6:20|IC,6:33,6:51</Time><Time hour="7">7:05,7:19,7:33,7:47</Time><Time hour="8">8:01,8:15,8:29,8:35,8:49</Time><Time hour="9">9:03,9:17,9:29,9:39,9:53</Time><Time hour="10">10:07,10:19,10:32,10:44,10:56</Time><Time hour="11">11:08,11:20,11:33,11:45,11:57</Time><Time hour="12">12:03,12:21,12:34,12:47</Time><Time hour="13">13:00,13:11,13:23,13:35,13:48</Time><Time hour="14">14:00,14:12,14:24,14:37,14:49</Time><Time hour="15">15:02,15:14,15:26,15:38,15:50</Time><Time hour="16">16:03,16:15,16:27,16:39,16:52</Time><Time hour="17">17:04,17:17,17:29,17:41,17:53</Time><Time hour="18">18:05,18:18,18:30,18:42,18:54</Time><Time hour="19">19:07,19:19,19:32,19:44,19:56</Time><Time hour="20">20:08,20:20,20:33,20:45,20:57</Time><Time hour="21">21:09,21:22,21:34,21:47,21:59</Time><Time hour="22">22:12,22:25,22:39,22:53</Time><Time hour="23">23:07,23:24,23:39,23:54</Time><Time hour="24">0:10</Time></Schedule></Station>