<?xml version="1.0" encoding="UTF-8" standalone="no"?><Station><Status state="OK"/><Number>3022</Number><Name>МЕТРОСТАНЦИЯ Г.М. ДИМИТРОВ</Name><Direction>м.Младост 1 - м.Обеля - м.Джеймс Баучер</Direction><Coordinates><Latitude>42.662888</Latitude><Longitude>23.357899</Longitude></Coordinates><Schedule day="Weekday"><Time hour="4"/><Time hour="5">5:30,5:43,5:48,5:56</Time><Time hour="6">6:03,6:09,6:16,6:22,6:29,6:35,6:42,6:48,6:55</Time><Time hour="7">7:01,7:07,7:11|IC,7:14,7:18|IC,7:21,7:24|IC,7:27,7:31|IC,7:34,7:37|IC,7:40,7:44,7:47|IC,7:50|IC,7:53,7:57|IC,7:59</Time><Time hour="8">8:03|IC,8:06,8:10|IC,8:13,8:16|IC,8:19,8:23|IC,8:26,8:29|IC,8:32,8:36|IC,8:39,8:42|IC,8:45,8:49|IC,8:51,8:55|IC,8:58</Time><Time hour="9">9:02|IC,9:05,9:08|IC,9:11,9:15|IC,9:18,9:21|IC,9:24,9:28|IC,9:31,9:34|IC,9:37,9:41|IC,9:44,9:47|IC,9:50,9:54|IC,9:57</Time><Time hour="10">10:00|IC,10:03|IC,10:07,10:10|IC,10:13,10:16|IC,10:20,10:23|IC,10:28|IC,10:31,10:35|IC,10:40|IC,10:44,10:48|IC,10:53,10:57|IC</Time><Time hour="11">11:02,11:06|IC,11:11,11:15|IC,11:20,11:24|IC,11:29,11:33|IC,11:38,11:42|IC,11:47,11:51|IC,11:56</Time><Time hour="12">12:00|IC,12:05,12:09|IC,12:14,12:18|IC,12:23,12:27|IC,12:32,12:36|IC,12:41,12:45|IC,12:50,12:54|IC,12:58</Time><Time hour="13">13:03|IC,13:07,13:16,13:18|IC,13:21|IC,13:25,13:30|IC,13:34,13:39|IC,13:43,13:48|IC,13:52,13:57|IC</Time><Time hour="14">14:01,14:06|IC,14:10,14:15|IC,14:19,14:24|IC,14:28,14:33|IC,14:37,14:42|IC,14:46,14:51|IC,14:55</Time><Time hour="15">15:00|IC,15:04,15:09|IC,15:13,15:17,15:22,15:27|IC,15:31,15:35|IC,15:40,15:44|IC,15:49,15:53|IC,15:58</Time><Time hour="16">16:02|IC,16:07,16:11|IC,16:16,16:20|IC,16:25,16:29,16:34|IC,16:38,16:43|IC,16:47,16:52,16:56|IC</Time><Time hour="17">17:01,17:05|IC,17:10,17:14|IC,17:19,17:22|IC,17:26,17:30|IC,17:34,17:38|IC,17:40|IC,17:42,17:50,17:54|IC,17:58</Time><Time hour="18">18:02|IC,18:06,18:10|IC,18:14,18:18|IC,18:22,18:26|IC,18:31,18:34|IC,18:38,18:42|IC,18:46,18:50|IC,18:54,18:58|IC</Time><Time hour="19">19:02,19:06|IC,19:10,19:14|IC,19:18,19:22|IC,19:26,19:30|IC,19:34,19:38|IC,19:42,19:46|IC,19:50,19:54|IC,19:58</Time><Time hour="20">20:02|IC,20:06,20:10|IC,20:14,20:17|IC,20:22,20:26|IC,20:30,20:34|IC,20:38,20:42|IC,20:46,20:51|IC,20:55,20:59|IC</Time><Time hour="21">21:04,21:08|IC,21:13,21:18|IC,21:22,21:28|IC,21:32,21:37|IC,21:42,21:48|IC,21:53</Time><Time hour="22">22:00|IC,22:06,22:13|IC,22:20,22:27|IC,22:35,22:39|IC,22:47,22:53|IC</Time><Time hour="23">23:00,23:06|IC,23:12,23:18|IC,23:25,23:31|IC,23:39|IC,23:45|IC,23:53|IC,23:59|IC</Time><Time hour="24">24:07|IC</Time></Schedule><Schedule day="Holiday"><Time hour="4"/><Time hour="5">5:34,5:44,5:51|IC,5:59</Time><Time hour="6">6:06|IC,6:13,6:21|IC,6:28,6:35|IC,6:42,6:49|IC,6:57</Time><Time hour="7">7:04|IC,7:12,7:19|IC,7:26,7:34,7:41|IC,7:47,7:56|IC</Time><Time hour="8">8:01,8:12,8:19,8:26|IC,8:34,8:40|IC,8:48,8:54|IC</Time><Time hour="9">9:00,9:09,9:15|IC,9:23,9:28|IC,9:36,9:41|IC,9:49,9:53|IC</Time><Time hour="10">10:00,10:06|IC,10:13,10:17|IC,10:24,10:29|IC,10:36,10:41|IC,10:48,10:54|IC</Time><Time hour="11">11:00,11:06|IC,11:12,11:18|IC,11:24,11:30|IC,11:36,11:42|IC,11:48,11:54|IC</Time><Time hour="12">12:00,12:06|IC,12:12,12:18|IC,12:24,12:30|IC,12:36,12:42|IC,12:48,12:54|IC</Time><Time hour="13">13:00,13:06|IC,13:12,13:18|IC,13:24,13:30|IC,13:36,13:42|IC,13:48,13:54|IC</Time><Time hour="14">14:00,14:06|IC,14:12,14:18|IC,14:24,14:30|IC,14:36,14:42|IC,14:48,14:54|IC</Time><Time hour="15">15:00,15:06|IC,15:12,15:18|IC,15:24,15:30|IC,15:36,15:42|IC,15:48,15:54|IC</Time><Time hour="16">16:00,16:06|IC,16:12,16:18|IC,16:24,16:30|IC,16:36,16:42|IC,16:48,16:54|IC</Time><Time hour="17">17:00,17:06|IC,17:12,17:18|IC,17:24,17:30|IC,17:36,17:42|IC,17:48,17:54|IC</Time><Time hour="18">18:00,18:06|IC,18:12,18:18|IC,18:24,18:30|IC,18:36,18:42|IC,18:48,18:54|IC</Time><Time hour="19">19:00,19:06|IC,19:12,19:18|IC,19:24,19:30|IC,19:36,19:42|IC,19:48,19:55|IC</Time><Time hour="20">20:00,20:06|IC,20:13,20:20|IC,20:26,20:31|IC,20:38,20:44|IC,20:51,20:57|IC</Time><Time hour="21">21:04,21:11|IC,21:18,21:25|IC,21:32,21:40|IC,21:47,21:54|IC</Time><Time hour="22">22:02,22:09|IC,22:17,22:24|IC,22:32,22:39|IC,22:47,22:54|IC</Time><Time hour="23">23:02,23:08,23:15|IC,23:22|IC,23:30|IC,23:37|IC,23:44|IC,23:59|IC</Time><Time hour="24"/></Schedule></Station>